flarelette_jwt/__init__.py
flarelette_jwt/adapters.py
flarelette_jwt/env.py
flarelette_jwt/explicit.py
flarelette_jwt/high.py
flarelette_jwt/secret.py
flarelette_jwt/sign.py
flarelette_jwt/util.py
flarelette_jwt/verify.py
flarelette_jwt-1.12.0.dist-info/licenses/LICENSE
flarelette_jwt-1.12.0.dist-info/METADATA
flarelette_jwt-1.12.0.dist-info/WHEEL
flarelette_jwt-1.12.0.dist-info/entry_points.txt
flarelette_jwt-1.12.0.dist-info/top_level.txt
flarelette_jwt-1.12.0.dist-info/RECORD
