Metadata-Version: 2.4
Name: flarelette-jwt
Version: 1.12.0
Summary: Environment-driven JWT authentication for Cloudflare Workers Python with secret-name indirection
Author-email: Chris Lyons <chris@chrislyons.dev>
License: MIT
Project-URL: Homepage, https://github.com/chrislyons-dev/flarelette-jwt-kit
Project-URL: Repository, https://github.com/chrislyons-dev/flarelette-jwt-kit
Project-URL: Issues, https://github.com/chrislyons-dev/flarelette-jwt-kit/issues
Project-URL: Documentation, https://github.com/chrislyons-dev/flarelette-jwt-kit#readme
Keywords: jwt,authentication,cloudflare,workers,edge,hs512,eddsa,ed25519,pyodide,flarelette
Classifier: Development Status :: 4 - Beta
Classifier: Intended Audience :: Developers
Classifier: License :: OSI Approved :: MIT License
Classifier: Programming Language :: Python :: 3
Classifier: Programming Language :: Python :: 3.11
Classifier: Programming Language :: Python :: 3.12
Classifier: Topic :: Software Development :: Libraries :: Python Modules
Classifier: Topic :: Security
Requires-Python: >=3.11
License-File: LICENSE
Requires-Dist: setuptools
Dynamic: license-file
